[{"rank": "1", "did": "DB01403", "name": "Methotrimeprazine"}, {"rank": "2", "did": "DB00281", "name": "Lidocaine"}, {"rank": "3", "did": "DB06774", "name": "Capsaicin"}, {"rank": "4", "did": "DB00669", "name": "Sumatriptan"}, {"rank": "5", "did": "DB02772", "name": "Sucrose"}, {"rank": "6", "did": "DB09085", "name": "Tetracaine"}, {"rank": "7", "did": "DB00934", "name": "Maprotiline"}, {"rank": "8", "did": "DB02513", "name": "Thymol"}, {"rank": "9", "did": "DB01065", "name": "Melatonin"}, {"rank": "10", "did": "DB00166", "name": "Lipoic acid"}, {"rank": "11", "did": "DB01019", "name": "Bethanechol"}, {"rank": "12", "did": "DB00391", "name": "Sulpiride"}, {"rank": "13", "did": "DB00907", "name": "Cocaine"}, {"rank": "14", "did": "DB00252", "name": "Phenytoin"}, {"rank": "15", "did": "DB04882", "name": "Edotecarin"}, {"rank": "16", "did": "DB11672", "name": "Curcumin"}, {"rank": "17", "did": "DB00477", "name": "Chlorpromazine"}, {"rank": "18", "did": "DB00181", "name": "Baclofen"}, {"rank": "19", "did": "DB09153", "name": "Sodium chloride"}, {"rank": "20", "did": "DB00554", "name": "Piroxicam"}, {"rank": "21", "did": "DB00215", "name": "Citalopram"}, {"rank": "22", "did": "DB09341", "name": "Dextrose, unspecified form"}, {"rank": "23", "did": "DB00704", "name": "Naltrexone"}, {"rank": "24", "did": "DB00490", "name": "Buspirone"}, {"rank": "25", "did": "DB00927", "name": "Famotidine"}, {"rank": "26", "did": "DB01151", "name": "Desipramine"}, {"rank": "27", "did": "DB02530", "name": "gamma-Aminobutyric acid"}, {"rank": "28", "did": "DB01406", "name": "Danazol"}, {"rank": "29", "did": "DB01143", "name": "Amifostine"}, {"rank": "30", "did": "DB01645", "name": "Genistein"}, {"rank": "31", "did": "DB01400", "name": "Neostigmine"}, {"rank": "32", "did": "DB00795", "name": "Sulfasalazine"}, {"rank": "33", "did": "DB01100", "name": "Pimozide"}, {"rank": "34", "did": "DB02587", "name": "Colforsin"}, {"rank": "35", "did": "DB03904", "name": "Urea"}, {"rank": "36", "did": "DB00135", "name": "Tyrosine"}, {"rank": "37", "did": "DB00345", "name": "Aminohippuric acid"}, {"rank": "38", "did": "DB00715", "name": "Paroxetine"}, {"rank": "39", "did": "DB01104", "name": "Sertraline"}, {"rank": "40", "did": "DB00847", "name": "Cysteamine"}, {"rank": "41", "did": "DB11387", "name": "Chloroform"}, {"rank": "42", "did": "DB00575", "name": "Clonidine"}, {"rank": "43", "did": "DB11118", "name": "Ammonia"}, {"rank": "44", "did": "DB00458", "name": "Imipramine"}, {"rank": "45", "did": "DB00812", "name": "Phenylbutazone"}, {"rank": "46", "did": "DB00285", "name": "Venlafaxine"}, {"rank": "47", "did": "DB00421", "name": "Spironolactone"}, {"rank": "48", "did": "DB00783", "name": "Estradiol"}, {"rank": "49", "did": "DB01046", "name": "Lubiprostone"}, {"rank": "50", "did": "DB01373", "name": "Calcium"}]