[{"rank": "1", "did": "DB00201", "name": "Caffeine"}, {"rank": "2", "did": "DB00571", "name": "Propranolol"}, {"rank": "3", "did": "DB11846", "name": "Creatinine"}, {"rank": "4", "did": "DB12028", "name": "Broxuridine"}, {"rank": "5", "did": "DB11118", "name": "Ammonia"}, {"rank": "6", "did": "DB00706", "name": "Tamsulosin"}, {"rank": "7", "did": "DB04540", "name": "Cholesterol"}, {"rank": "8", "did": "DB01026", "name": "Ketoconazole"}, {"rank": "9", "did": "DB00834", "name": "Mifepristone"}, {"rank": "10", "did": "DB00985", "name": "Dimenhydrinate"}, {"rank": "11", "did": "DB00181", "name": "Baclofen"}, {"rank": "12", "did": "DB07392", "name": "Atrazine"}, {"rank": "13", "did": "DB01065", "name": "Melatonin"}, {"rank": "14", "did": "DB00783", "name": "Estradiol"}, {"rank": "15", "did": "DB00117", "name": "Histidine"}, {"rank": "16", "did": "DB00915", "name": "Amantadine"}, {"rank": "17", "did": "DB00624", "name": "Testosterone"}, {"rank": "18", "did": "DB00373", "name": "Timolol"}, {"rank": "19", "did": "DB13956", "name": "Estradiol valerate"}, {"rank": "20", "did": "DB00650", "name": "Leucovorin"}, {"rank": "21", "did": "DB09389", "name": "Norgestrel"}, {"rank": "22", "did": "DB00138", "name": "Cystine"}, {"rank": "23", "did": "DB00122", "name": "Choline"}, {"rank": "24", "did": "DB04573", "name": "Estriol"}, {"rank": "25", "did": "DB02056", "name": "Prostaglandin D2"}, {"rank": "26", "did": "DB14702", "name": "Sodium metavanadate"}, {"rank": "27", "did": "DB01524", "name": "Androstenediol"}, {"rank": "28", "did": "DB00717", "name": "Norethisterone"}, {"rank": "29", "did": "DB00254", "name": "Doxycycline"}, {"rank": "30", "did": "DB01009", "name": "Ketoprofen"}, {"rank": "31", "did": "DB00898", "name": "Ethanol"}, {"rank": "32", "did": "DB00847", "name": "Cysteamine"}, {"rank": "33", "did": "DB00118", "name": "Ademetionine"}, {"rank": "34", "did": "DB06823", "name": "Tiopronin"}, {"rank": "35", "did": "DB12422", "name": "Sulforaphane"}, {"rank": "36", "did": "DB00869", "name": "Dorzolamide"}, {"rank": "37", "did": "DB00576", "name": "Sulfamethizole"}, {"rank": "38", "did": "DB11768", "name": "Zytron"}, {"rank": "39", "did": "DB13318", "name": "Demecolcine"}, {"rank": "40", "did": "DB00140", "name": "Riboflavin"}, {"rank": "41", "did": "DB00499", "name": "Flutamide"}, {"rank": "42", "did": "DB00442", "name": "Entecavir"}, {"rank": "43", "did": "DB00603", "name": "Medroxyprogesterone acetate"}, {"rank": "44", "did": "DB01078", "name": "Deslanoside"}, {"rank": "45", "did": "DB01395", "name": "Drospirenone"}, {"rank": "46", "did": "DB00422", "name": "Methylphenidate"}, {"rank": "47", "did": "DB09072", "name": "Sodium oxybate"}, {"rank": "48", "did": "DB00511", "name": "Acetyldigitoxin"}, {"rank": "49", "did": "DB01844", "name": "N,N-dimethylformamide"}, {"rank": "50", "did": "DB00855", "name": "Aminolevulinic acid"}]