[{"rank": "1", "did": "DB00898", "name": "Ethanol"}, {"rank": "2", "did": "DB00295", "name": "Morphine"}, {"rank": "3", "did": "DB01394", "name": "Colchicine"}, {"rank": "4", "did": "DB00829", "name": "Diazepam"}, {"rank": "5", "did": "DB00755", "name": "Tretinoin"}, {"rank": "6", "did": "DB00982", "name": "Isotretinoin"}, {"rank": "7", "did": "DB00313", "name": "Valproic acid"}, {"rank": "8", "did": "DB00563", "name": "Methotrexate"}, {"rank": "9", "did": "DB00877", "name": "Sirolimus"}, {"rank": "10", "did": "DB00907", "name": "Cocaine"}, {"rank": "11", "did": "DB00819", "name": "Acetazolamide"}, {"rank": "12", "did": "DB00158", "name": "Folic acid"}, {"rank": "13", "did": "DB00867", "name": "Ritodrine"}, {"rank": "14", "did": "DB00564", "name": "Carbamazepine"}, {"rank": "15", "did": "DB00277", "name": "Theophylline"}, {"rank": "16", "did": "DB00122", "name": "Choline"}, {"rank": "17", "did": "DB00571", "name": "Propranolol"}, {"rank": "18", "did": "DB00171", "name": "ATP"}, {"rank": "19", "did": "DB00694", "name": "Daunorubicin"}, {"rank": "20", "did": "DB09502", "name": "Fludeoxyglucose (18F)"}, {"rank": "21", "did": "DB09140", "name": "Oxygen"}, {"rank": "22", "did": "DB04216", "name": "Quercetin"}, {"rank": "23", "did": "DB00201", "name": "Caffeine"}, {"rank": "24", "did": "DB04115", "name": "Berberine"}, {"rank": "25", "did": "DB14513", "name": "Magnesium"}, {"rank": "26", "did": "DB06690", "name": "Nitrous oxide"}, {"rank": "27", "did": "DB00682", "name": "Warfarin"}, {"rank": "28", "did": "DB00987", "name": "Cytarabine"}, {"rank": "29", "did": "DB00988", "name": "Dopamine"}, {"rank": "30", "did": "DB00925", "name": "Phenoxybenzamine"}, {"rank": "31", "did": "DB00531", "name": "Cyclophosphamide"}, {"rank": "32", "did": "DB01174", "name": "Phenobarbital"}, {"rank": "33", "did": "DB01115", "name": "Nifedipine"}, {"rank": "34", "did": "DB00550", "name": "Propylthiouracil"}, {"rank": "35", "did": "DB00252", "name": "Phenytoin"}, {"rank": "36", "did": "DB11133", "name": "Omega-3 fatty acids"}, {"rank": "37", "did": "DB00345", "name": "Aminohippuric acid"}, {"rank": "38", "did": "DB00316", "name": "Acetaminophen"}, {"rank": "39", "did": "DB01373", "name": "Calcium"}, {"rank": "40", "did": "DB00435", "name": "Nitric Oxide"}, {"rank": "41", "did": "DB00182", "name": "Amphetamine"}, {"rank": "42", "did": "DB12116", "name": "Epigallocatechin gallate"}, {"rank": "43", "did": "DB00459", "name": "Acitretin"}, {"rank": "44", "did": "DB04557", "name": "Arachidonic Acid"}, {"rank": "45", "did": "DB00035", "name": "Desmopressin"}, {"rank": "46", "did": "DB02772", "name": "Sucrose"}, {"rank": "47", "did": "DB01065", "name": "Melatonin"}, {"rank": "48", "did": "DB00437", "name": "Allopurinol"}, {"rank": "49", "did": "DB00723", "name": "Methoxamine"}, {"rank": "50", "did": "DB00783", "name": "Estradiol"}]