[{"rank": "1", "did": "DB00331", "name": "Metformin"}, {"rank": "2", "did": "DB00926", "name": "Etretinate"}, {"rank": "3", "did": "DB02315", "name": "Cyclic GMP"}, {"rank": "4", "did": "DB00328", "name": "Indomethacin"}, {"rank": "5", "did": "DB09341", "name": "Dextrose, unspecified form"}, {"rank": "6", "did": "DB00443", "name": "Betamethasone"}, {"rank": "7", "did": "DB00860", "name": "Prednisolone"}, {"rank": "8", "did": "DB00531", "name": "Cyclophosphamide"}, {"rank": "9", "did": "DB00834", "name": "Mifepristone"}, {"rank": "10", "did": "DB00620", "name": "Triamcinolone"}, {"rank": "11", "did": "DB00641", "name": "Simvastatin"}, {"rank": "12", "did": "DB00959", "name": "Methylprednisolone"}, {"rank": "13", "did": "DB00763", "name": "Methimazole"}, {"rank": "14", "did": "DB04299", "name": "Maleic acid"}, {"rank": "15", "did": "DB00635", "name": "Prednisone"}, {"rank": "16", "did": "DB01041", "name": "Thalidomide"}, {"rank": "17", "did": "DB00459", "name": "Acitretin"}, {"rank": "18", "did": "DB01046", "name": "Lubiprostone"}, {"rank": "19", "did": "DB00410", "name": "Mupirocin"}, {"rank": "20", "did": "DB00741", "name": "Hydrocortisone"}, {"rank": "21", "did": "DB01216", "name": "Finasteride"}, {"rank": "22", "did": "DB01677", "name": "Fumaric acid"}, {"rank": "23", "did": "DB08895", "name": "Tofacitinib"}, {"rank": "24", "did": "DB00755", "name": "Tretinoin"}, {"rank": "25", "did": "DB00091", "name": "Cyclosporine"}, {"rank": "26", "did": "DB01296", "name": "Glucosamine"}, {"rank": "27", "did": "DB03057", "name": "Malonaldehyde"}, {"rank": "28", "did": "DB01234", "name": "Dexamethasone"}, {"rank": "29", "did": "DB00591", "name": "Fluocinolone acetonide"}, {"rank": "30", "did": "DB00400", "name": "Griseofulvin"}, {"rank": "31", "did": "DB00859", "name": "Penicillamine"}, {"rank": "32", "did": "DB01956", "name": "Taurine"}, {"rank": "33", "did": "DB09153", "name": "Sodium chloride"}, {"rank": "34", "did": "DB14507", "name": "Lithium citrate"}, {"rank": "35", "did": "DB12354", "name": "Imrecoxib"}, {"rank": "36", "did": "DB04422", "name": "Homocysteine"}, {"rank": "37", "did": "DB00936", "name": "Salicylic acid"}, {"rank": "38", "did": "DB02300", "name": "Calcipotriol"}, {"rank": "39", "did": "DB09322", "name": "Zinc sulfate"}, {"rank": "40", "did": "DB06777", "name": "Chenodeoxycholic acid"}, {"rank": "41", "did": "DB03566", "name": "Spermidine"}, {"rank": "42", "did": "DB00571", "name": "Propranolol"}, {"rank": "43", "did": "DB11341", "name": "Ichthammol"}, {"rank": "44", "did": "DB13066", "name": "Liarozole"}, {"rank": "45", "did": "DB03604", "name": "Tiratricol"}, {"rank": "46", "did": "DB08809", "name": "Dichloroacetic acid"}, {"rank": "47", "did": "DB00324", "name": "Fluorometholone"}, {"rank": "48", "did": "DB14681", "name": "Cortisone"}, {"rank": "49", "did": "DB00550", "name": "Propylthiouracil"}, {"rank": "50", "did": "DB01373", "name": "Calcium"}]