[{"rank": "1", "did": "DB00624", "name": "Testosterone"}, {"rank": "2", "did": "DB00644", "name": "Gonadorelin"}, {"rank": "3", "did": "DB00421", "name": "Spironolactone"}, {"rank": "4", "did": "DB08839", "name": "Serotonin"}, {"rank": "5", "did": "DB00715", "name": "Paroxetine"}, {"rank": "6", "did": "DB00783", "name": "Estradiol"}, {"rank": "7", "did": "DB01065", "name": "Melatonin"}, {"rank": "8", "did": "DB00675", "name": "Tamoxifen"}, {"rank": "9", "did": "DB12898", "name": "Calcitonin eel"}, {"rank": "10", "did": "DB00091", "name": "Cyclosporine"}, {"rank": "11", "did": "DB00834", "name": "Mifepristone"}, {"rank": "12", "did": "DB04398", "name": "Lactic acid"}, {"rank": "13", "did": "DB05381", "name": "Histamine"}, {"rank": "14", "did": "DB00313", "name": "Valproic acid"}, {"rank": "15", "did": "DB00544", "name": "Fluorouracil"}, {"rank": "16", "did": "DB00550", "name": "Propylthiouracil"}, {"rank": "17", "did": "DB00286", "name": "Conjugated estrogens"}, {"rank": "18", "did": "DB13178", "name": "Inositol"}, {"rank": "19", "did": "DB01181", "name": "Ifosfamide"}, {"rank": "20", "did": "DB01536", "name": "Androstenedione"}, {"rank": "21", "did": "DB07392", "name": "Atrazine"}, {"rank": "22", "did": "DB11094", "name": "Vitamin D"}, {"rank": "23", "did": "DB00898", "name": "Ethanol"}, {"rank": "24", "did": "DB04540", "name": "Cholesterol"}, {"rank": "25", "did": "DB00927", "name": "Famotidine"}, {"rank": "26", "did": "DB00860", "name": "Prednisolone"}, {"rank": "27", "did": "DB00988", "name": "Dopamine"}, {"rank": "28", "did": "DB00864", "name": "Tacrolimus"}, {"rank": "29", "did": "DB01593", "name": "Zinc"}, {"rank": "30", "did": "DB00877", "name": "Sirolimus"}, {"rank": "31", "did": "DB09325", "name": "Sodium fluoride"}, {"rank": "32", "did": "DB01234", "name": "Dexamethasone"}, {"rank": "33", "did": "DB01586", "name": "Ursodeoxycholic acid"}, {"rank": "34", "did": "DB09130", "name": "Copper"}, {"rank": "35", "did": "DB00184", "name": "Nicotine"}, {"rank": "36", "did": "DB14085", "name": "Cadmium"}, {"rank": "37", "did": "DB00399", "name": "Zoledronic acid"}, {"rank": "38", "did": "DB11118", "name": "Ammonia"}, {"rank": "39", "did": "DB01645", "name": "Genistein"}, {"rank": "40", "did": "DB00636", "name": "Clofibrate"}, {"rank": "41", "did": "DB00181", "name": "Baclofen"}, {"rank": "42", "did": "DB00967", "name": "Desloratadine"}, {"rank": "43", "did": "DB00122", "name": "Choline"}, {"rank": "44", "did": "DB01373", "name": "Calcium"}, {"rank": "45", "did": "DB00515", "name": "Cisplatin"}, {"rank": "46", "did": "DB05383", "name": "Pimagedine"}, {"rank": "47", "did": "DB00163", "name": "Vitamin E"}, {"rank": "48", "did": "DB01200", "name": "Bromocriptine"}, {"rank": "49", "did": "DB13956", "name": "Estradiol valerate"}, {"rank": "50", "did": "DB00959", "name": "Methylprednisolone"}]