[{"rank": "1", "did": "DB00515", "name": "Cisplatin"}, {"rank": "2", "did": "DB00571", "name": "Propranolol"}, {"rank": "3", "did": "DB00682", "name": "Warfarin"}, {"rank": "4", "did": "DB00668", "name": "Epinephrine"}, {"rank": "5", "did": "DB00441", "name": "Gemcitabine"}, {"rank": "6", "did": "DB00396", "name": "Progesterone"}, {"rank": "7", "did": "DB00819", "name": "Acetazolamide"}, {"rank": "8", "did": "DB01221", "name": "Ketamine"}, {"rank": "9", "did": "DB00633", "name": "Dexmedetomidine"}, {"rank": "10", "did": "DB00572", "name": "Atropine"}, {"rank": "11", "did": "DB00834", "name": "Mifepristone"}, {"rank": "12", "did": "DB01016", "name": "Glyburide"}, {"rank": "13", "did": "DB00388", "name": "Phenylephrine"}, {"rank": "14", "did": "DB00898", "name": "Ethanol"}, {"rank": "15", "did": "DB00252", "name": "Phenytoin"}, {"rank": "16", "did": "DB02543", "name": "Pyrrole-2-Carboxylate"}, {"rank": "17", "did": "DB00125", "name": "Arginine"}, {"rank": "18", "did": "DB05381", "name": "Histamine"}, {"rank": "19", "did": "DB00171", "name": "ATP"}, {"rank": "20", "did": "DB00333", "name": "Methadone"}, {"rank": "21", "did": "DB12028", "name": "Broxuridine"}, {"rank": "22", "did": "DB00693", "name": "Fluorescein"}, {"rank": "23", "did": "DB00390", "name": "Digoxin"}, {"rank": "24", "did": "DB00201", "name": "Caffeine"}, {"rank": "25", "did": "DB00184", "name": "Nicotine"}, {"rank": "26", "did": "DB01174", "name": "Phenobarbital"}, {"rank": "27", "did": "DB06690", "name": "Nitrous oxide"}, {"rank": "28", "did": "DB05983", "name": "Bardoxolone methyl"}, {"rank": "29", "did": "DB00472", "name": "Fluoxetine"}, {"rank": "30", "did": "DB04485", "name": "Thymidine"}, {"rank": "31", "did": "DB01427", "name": "Amrinone"}, {"rank": "32", "did": "DB00945", "name": "Acetylsalicylic acid"}, {"rank": "33", "did": "DB00640", "name": "Adenosine"}, {"rank": "34", "did": "DB00818", "name": "Propofol"}, {"rank": "35", "did": "DB06641", "name": "Perifosine"}, {"rank": "36", "did": "DB00790", "name": "Perindopril"}, {"rank": "37", "did": "DB01181", "name": "Ifosfamide"}, {"rank": "38", "did": "DB01242", "name": "Clomipramine"}, {"rank": "39", "did": "DB00182", "name": "Amphetamine"}, {"rank": "40", "did": "DB04557", "name": "Arachidonic Acid"}, {"rank": "41", "did": "DB03310", "name": "Glutathione disulfide"}, {"rank": "42", "did": "DB00159", "name": "Icosapent"}, {"rank": "43", "did": "DB00623", "name": "Fluphenazine"}, {"rank": "44", "did": "DB00325", "name": "Nitroprusside"}, {"rank": "45", "did": "DB00502", "name": "Haloperidol"}, {"rank": "46", "did": "DB00368", "name": "Norepinephrine"}, {"rank": "47", "did": "DB01373", "name": "Calcium"}, {"rank": "48", "did": "DB01143", "name": "Amifostine"}, {"rank": "49", "did": "DB01118", "name": "Amiodarone"}, {"rank": "50", "did": "DB02010", "name": "Staurosporine"}]