[{"rank": "1", "did": "DB01235", "name": "Levodopa"}, {"rank": "2", "did": "DB00376", "name": "Trihexyphenidyl"}, {"rank": "3", "did": "DB01592", "name": "Iron"}, {"rank": "4", "did": "DB13132", "name": "Artemisinin"}, {"rank": "5", "did": "DB14522", "name": "Hydroxide ion"}, {"rank": "6", "did": "DB00368", "name": "Norepinephrine"}, {"rank": "7", "did": "DB11336", "name": "Kinetin"}, {"rank": "8", "did": "DB08844", "name": "Uric acid"}, {"rank": "9", "did": "DB01197", "name": "Captopril"}, {"rank": "10", "did": "DB01037", "name": "Selegiline"}, {"rank": "11", "did": "DB00627", "name": "Niacin"}, {"rank": "12", "did": "DB00184", "name": "Nicotine"}, {"rank": "13", "did": "DB00773", "name": "Etoposide"}, {"rank": "14", "did": "DB00877", "name": "Sirolimus"}, {"rank": "15", "did": "DB01068", "name": "Clonazepam"}, {"rank": "16", "did": "DB04398", "name": "Lactic acid"}, {"rank": "17", "did": "DB00584", "name": "Enalapril"}, {"rank": "18", "did": "DB04115", "name": "Berberine"}, {"rank": "19", "did": "DB00091", "name": "Cyclosporine"}, {"rank": "20", "did": "DB00714", "name": "Apomorphine"}, {"rank": "21", "did": "DB01186", "name": "Pergolide"}, {"rank": "22", "did": "DB00435", "name": "Nitric Oxide"}, {"rank": "23", "did": "DB01115", "name": "Nifedipine"}, {"rank": "24", "did": "DB06756", "name": "Betaine"}, {"rank": "25", "did": "DB05087", "name": "Ganaxolone"}, {"rank": "26", "did": "DB00388", "name": "Phenylephrine"}, {"rank": "27", "did": "DB04335", "name": "Inosine"}, {"rank": "28", "did": "DB00834", "name": "Mifepristone"}, {"rank": "29", "did": "DB12028", "name": "Broxuridine"}, {"rank": "30", "did": "DB14523", "name": "Phosphate ion"}, {"rank": "31", "did": "DB12310", "name": "Trehalose"}, {"rank": "32", "did": "DB00160", "name": "Alanine"}, {"rank": "33", "did": "DB11846", "name": "Creatinine"}, {"rank": "34", "did": "DB00981", "name": "Physostigmine"}, {"rank": "35", "did": "DB12412", "name": "Gemigliptin"}, {"rank": "36", "did": "DB00996", "name": "Gabapentin"}, {"rank": "37", "did": "DB00331", "name": "Metformin"}, {"rank": "38", "did": "DB11136", "name": "Chromium"}, {"rank": "39", "did": "DB00158", "name": "Folic acid"}, {"rank": "40", "did": "DB07392", "name": "Atrazine"}, {"rank": "41", "did": "DB00387", "name": "Procyclidine"}, {"rank": "42", "did": "DB03988", "name": "2,6-Diamino-Hexanoic Acid Amide"}, {"rank": "43", "did": "DB00541", "name": "Vincristine"}, {"rank": "44", "did": "DB00126", "name": "Ascorbic acid"}, {"rank": "45", "did": "DB01528", "name": "4-Methyl-2,5-dimethoxyamphetamine"}, {"rank": "46", "did": "DB14547", "name": "Chloride ion"}, {"rank": "47", "did": "DB13178", "name": "Inositol"}, {"rank": "48", "did": "DB01233", "name": "Metoclopramide"}, {"rank": "49", "did": "DB05381", "name": "Histamine"}, {"rank": "50", "did": "DB13919", "name": "Candesartan"}]