[{"rank": "1", "did": "DB00446", "name": "Chloramphenicol"}, {"rank": "2", "did": "DB01082", "name": "Streptomycin"}, {"rank": "3", "did": "DB00493", "name": "Cefotaxime"}, {"rank": "4", "did": "DB00781", "name": "Polymyxin B"}, {"rank": "5", "did": "DB01045", "name": "Rifampicin"}, {"rank": "6", "did": "DB14681", "name": "Cortisone"}, {"rank": "7", "did": "DB01212", "name": "Ceftriaxone"}, {"rank": "8", "did": "DB00358", "name": "Mefloquine"}, {"rank": "9", "did": "DB00688", "name": "Mycophenolate mofetil"}, {"rank": "10", "did": "DB00945", "name": "Acetylsalicylic acid"}, {"rank": "11", "did": "DB00997", "name": "Doxorubicin"}, {"rank": "12", "did": "DB06771", "name": "Besifloxacin"}, {"rank": "13", "did": "DB00355", "name": "Aztreonam"}, {"rank": "14", "did": "DB05245", "name": "Silver sulfadiazine"}, {"rank": "15", "did": "DB00987", "name": "Cytarabine"}, {"rank": "16", "did": "DB11094", "name": "Vitamin D"}, {"rank": "17", "did": "DB01394", "name": "Colchicine"}, {"rank": "18", "did": "DB00500", "name": "Tolmetin"}, {"rank": "19", "did": "DB00811", "name": "Ribavirin"}, {"rank": "20", "did": "DB09093", "name": "Chlortetracycline"}, {"rank": "21", "did": "DB00563", "name": "Methotrexate"}, {"rank": "22", "did": "DB00608", "name": "Chloroquine"}, {"rank": "23", "did": "DB00635", "name": "Prednisone"}, {"rank": "24", "did": "DB00134", "name": "Methionine"}, {"rank": "25", "did": "DB01373", "name": "Calcium"}, {"rank": "26", "did": "DB06219", "name": "Dalbavancin"}, {"rank": "27", "did": "DB00438", "name": "Ceftazidime"}, {"rank": "28", "did": "DB00330", "name": "Ethambutol"}, {"rank": "29", "did": "DB00712", "name": "Flurbiprofen"}, {"rank": "30", "did": "DB14507", "name": "Lithium citrate"}, {"rank": "31", "did": "DB00993", "name": "Azathioprine"}, {"rank": "32", "did": "DB01234", "name": "Dexamethasone"}, {"rank": "33", "did": "DB00787", "name": "Acyclovir"}, {"rank": "34", "did": "DB01118", "name": "Amiodarone"}, {"rank": "35", "did": "DB00798", "name": "Gentamicin"}, {"rank": "36", "did": "DB01053", "name": "Benzylpenicillin"}, {"rank": "37", "did": "DB01452", "name": "Diamorphine"}, {"rank": "38", "did": "DB00515", "name": "Cisplatin"}, {"rank": "39", "did": "DB00181", "name": "Baclofen"}, {"rank": "40", "did": "DB00440", "name": "Trimethoprim"}, {"rank": "41", "did": "DB00994", "name": "Neomycin"}, {"rank": "42", "did": "DB11127", "name": "Selenious acid"}, {"rank": "43", "did": "DB00148", "name": "Creatine"}, {"rank": "44", "did": "DB09241", "name": "Methylene blue"}, {"rank": "45", "did": "DB04630", "name": "Aldosterone"}, {"rank": "46", "did": "DB06461", "name": "Squalamine"}, {"rank": "47", "did": "DB00959", "name": "Methylprednisolone"}, {"rank": "48", "did": "DB01339", "name": "Vecuronium"}, {"rank": "49", "did": "DB09130", "name": "Copper"}, {"rank": "50", "did": "DB00692", "name": "Phentolamine"}]