[{"rank": "1", "did": "DB09140", "name": "Oxygen"}, {"rank": "2", "did": "DB01077", "name": "Etidronic acid"}, {"rank": "3", "did": "DB00396", "name": "Progesterone"}, {"rank": "4", "did": "DB04297", "name": "Trichostatin A"}, {"rank": "5", "did": "DB00435", "name": "Nitric Oxide"}, {"rank": "6", "did": "DB12866", "name": "Pradigastat"}, {"rank": "7", "did": "DB00437", "name": "Allopurinol"}, {"rank": "8", "did": "DB00184", "name": "Nicotine"}, {"rank": "9", "did": "DB08621", "name": "Thiamphenicol"}, {"rank": "10", "did": "DB00790", "name": "Perindopril"}, {"rank": "11", "did": "DB06285", "name": "Teriparatide"}, {"rank": "12", "did": "DB01008", "name": "Busulfan"}, {"rank": "13", "did": "DB05382", "name": "Iodine"}, {"rank": "14", "did": "DB00104", "name": "Octreotide"}, {"rank": "15", "did": "DB00583", "name": "Levocarnitine"}, {"rank": "16", "did": "DB14081", "name": "Asiaticoside"}, {"rank": "17", "did": "DB13044", "name": "Gossypol"}, {"rank": "18", "did": "DB12358", "name": "Enbucrilate"}, {"rank": "19", "did": "DB00806", "name": "Pentoxifylline"}, {"rank": "20", "did": "DB00456", "name": "Cefalotin"}, {"rank": "21", "did": "DB01427", "name": "Amrinone"}, {"rank": "22", "did": "DB00898", "name": "Ethanol"}, {"rank": "23", "did": "DB01229", "name": "Paclitaxel"}, {"rank": "24", "did": "DB00869", "name": "Dorzolamide"}, {"rank": "25", "did": "DB09069", "name": "Trimetazidine"}, {"rank": "26", "did": "DB00250", "name": "Dapsone"}, {"rank": "27", "did": "DB00682", "name": "Warfarin"}, {"rank": "28", "did": "DB00945", "name": "Acetylsalicylic acid"}, {"rank": "29", "did": "DB00928", "name": "Azacitidine"}, {"rank": "30", "did": "DB02543", "name": "Pyrrole-2-Carboxylate"}, {"rank": "31", "did": "DB00722", "name": "Lisinopril"}, {"rank": "32", "did": "DB13242", "name": "Bucladesine"}, {"rank": "33", "did": "DB01022", "name": "Phylloquinone"}, {"rank": "34", "did": "DB00163", "name": "Vitamin E"}, {"rank": "35", "did": "DB00126", "name": "Ascorbic acid"}, {"rank": "36", "did": "DB15995", "name": "Nitric acid"}, {"rank": "37", "did": "DB00974", "name": "Edetic acid"}, {"rank": "38", "did": "DB01070", "name": "Dihydrotachysterol"}, {"rank": "39", "did": "DB00693", "name": "Fluorescein"}, {"rank": "40", "did": "DB01592", "name": "Iron"}, {"rank": "41", "did": "DB00380", "name": "Dexrazoxane"}, {"rank": "42", "did": "DB01115", "name": "Nifedipine"}, {"rank": "43", "did": "DB02527", "name": "Cyclic adenosine monophosphate"}, {"rank": "44", "did": "DB02300", "name": "Calcipotriol"}, {"rank": "45", "did": "DB04540", "name": "Cholesterol"}, {"rank": "46", "did": "DB09302", "name": "Alirocumab"}, {"rank": "47", "did": "DB00035", "name": "Desmopressin"}, {"rank": "48", "did": "DB00864", "name": "Tacrolimus"}, {"rank": "49", "did": "DB13472", "name": "Cyclofenil"}, {"rank": "50", "did": "DB00877", "name": "Sirolimus"}]