[{"rank": "1", "did": "DB00007", "name": "Leuprolide"}, {"rank": "2", "did": "DB00014", "name": "Goserelin"}, {"rank": "3", "did": "DB00286", "name": "Conjugated estrogens"}, {"rank": "4", "did": "DB01196", "name": "Estramustine"}, {"rank": "5", "did": "DB00675", "name": "Tamoxifen"}, {"rank": "6", "did": "DB00290", "name": "Bleomycin"}, {"rank": "7", "did": "DB01181", "name": "Ifosfamide"}, {"rank": "8", "did": "DB00958", "name": "Carboplatin"}, {"rank": "9", "did": "DB01229", "name": "Paclitaxel"}, {"rank": "10", "did": "DB00515", "name": "Cisplatin"}, {"rank": "11", "did": "DB00603", "name": "Medroxyprogesterone acetate"}, {"rank": "12", "did": "DB00783", "name": "Estradiol"}, {"rank": "13", "did": "DB00894", "name": "Testolactone"}, {"rank": "14", "did": "DB01268", "name": "Sunitinib"}, {"rank": "15", "did": "DB00531", "name": "Cyclophosphamide"}, {"rank": "16", "did": "DB09278", "name": "Activated charcoal"}, {"rank": "17", "did": "DB05260", "name": "Gallium nitrate"}, {"rank": "18", "did": "DB03496", "name": "Alvocidib"}, {"rank": "19", "did": "DB00091", "name": "Cyclosporine"}, {"rank": "20", "did": "DB01005", "name": "Hydroxyurea"}, {"rank": "21", "did": "DB01248", "name": "Docetaxel"}, {"rank": "22", "did": "DB00352", "name": "Tioguanine"}, {"rank": "23", "did": "DB00563", "name": "Methotrexate"}, {"rank": "24", "did": "DB00997", "name": "Doxorubicin"}, {"rank": "25", "did": "DB00255", "name": "Diethylstilbestrol"}, {"rank": "26", "did": "DB00541", "name": "Vincristine"}, {"rank": "27", "did": "DB00104", "name": "Octreotide"}, {"rank": "28", "did": "DB04297", "name": "Trichostatin A"}, {"rank": "29", "did": "DB00987", "name": "Cytarabine"}, {"rank": "30", "did": "DB14523", "name": "Phosphate ion"}, {"rank": "31", "did": "DB00441", "name": "Gemcitabine"}, {"rank": "32", "did": "DB05767", "name": "Andrographolide"}, {"rank": "33", "did": "DB00917", "name": "Dinoprostone"}, {"rank": "34", "did": "DB01420", "name": "Testosterone propionate"}, {"rank": "35", "did": "DB00361", "name": "Vinorelbine"}, {"rank": "36", "did": "DB00910", "name": "Paricalcitol"}, {"rank": "37", "did": "DB13528", "name": "Chlormadinone"}, {"rank": "38", "did": "DB01050", "name": "Ibuprofen"}, {"rank": "39", "did": "DB00357", "name": "Aminoglutethimide"}, {"rank": "40", "did": "DB06266", "name": "Lonidamine"}, {"rank": "41", "did": "DB00446", "name": "Chloramphenicol"}, {"rank": "42", "did": "DB12754", "name": "Iodide"}, {"rank": "43", "did": "DB00655", "name": "Estrone"}, {"rank": "44", "did": "DB00396", "name": "Progesterone"}, {"rank": "45", "did": "DB03566", "name": "Spermidine"}, {"rank": "46", "did": "DB00635", "name": "Prednisone"}, {"rank": "47", "did": "DB10580", "name": "Tea leaf"}, {"rank": "48", "did": "DB12946", "name": "DPCPX"}, {"rank": "49", "did": "DB00834", "name": "Mifepristone"}, {"rank": "50", "did": "DB04796", "name": "Inecalcitol"}]