[{"rank": "1", "did": "DB00819", "name": "Acetazolamide"}, {"rank": "2", "did": "DB00627", "name": "Niacin"}, {"rank": "3", "did": "DB15050", "name": "Neopterin"}, {"rank": "4", "did": "DB00583", "name": "Levocarnitine"}, {"rank": "5", "did": "DB09341", "name": "Dextrose, unspecified form"}, {"rank": "6", "did": "DB00973", "name": "Ezetimibe"}, {"rank": "7", "did": "DB09270", "name": "Ubidecarenone"}, {"rank": "8", "did": "DB04540", "name": "Cholesterol"}, {"rank": "9", "did": "DB01241", "name": "Gemfibrozil"}, {"rank": "10", "did": "DB00635", "name": "Prednisone"}, {"rank": "11", "did": "DB04272", "name": "Citric acid"}, {"rank": "12", "did": "DB00636", "name": "Clofibrate"}, {"rank": "13", "did": "DB00435", "name": "Nitric Oxide"}, {"rank": "14", "did": "DB11846", "name": "Creatinine"}, {"rank": "15", "did": "DB00158", "name": "Folic acid"}, {"rank": "16", "did": "DB00227", "name": "Lovastatin"}, {"rank": "17", "did": "DB04422", "name": "Homocysteine"}, {"rank": "18", "did": "DB02527", "name": "Cyclic adenosine monophosphate"}, {"rank": "19", "did": "DB00140", "name": "Riboflavin"}, {"rank": "20", "did": "DB03128", "name": "Acetylcholine"}, {"rank": "21", "did": "DB00640", "name": "Adenosine"}, {"rank": "22", "did": "DB00459", "name": "Acitretin"}, {"rank": "23", "did": "DB00437", "name": "Allopurinol"}, {"rank": "24", "did": "DB00451", "name": "Levothyroxine"}, {"rank": "25", "did": "DB00641", "name": "Simvastatin"}, {"rank": "26", "did": "DB14128", "name": "Nadide"}, {"rank": "27", "did": "DB02315", "name": "Cyclic GMP"}, {"rank": "28", "did": "DB09140", "name": "Oxygen"}, {"rank": "29", "did": "DB00163", "name": "Vitamin E"}, {"rank": "30", "did": "DB00770", "name": "Alprostadil"}, {"rank": "31", "did": "DB03904", "name": "Urea"}, {"rank": "32", "did": "DB01103", "name": "Quinacrine"}, {"rank": "33", "did": "DB00155", "name": "Citrulline"}, {"rank": "34", "did": "DB14160", "name": "Titanium"}, {"rank": "35", "did": "DB00171", "name": "ATP"}, {"rank": "36", "did": "DB00148", "name": "Creatine"}, {"rank": "37", "did": "DB05262", "name": "Oxypurinol"}, {"rank": "38", "did": "DB00143", "name": "Glutathione"}, {"rank": "39", "did": "DB11866", "name": "Romosozumab"}, {"rank": "40", "did": "DB09421", "name": "Protirelin"}, {"rank": "41", "did": "DB01775", "name": "Dihydroxyacetone"}, {"rank": "42", "did": "DB01393", "name": "Bezafibrate"}, {"rank": "43", "did": "DB00608", "name": "Chloroquine"}, {"rank": "44", "did": "DB01085", "name": "Pilocarpine"}, {"rank": "45", "did": "DB00126", "name": "Ascorbic acid"}, {"rank": "46", "did": "DB00813", "name": "Fentanyl"}, {"rank": "47", "did": "DB09152", "name": "Nitrogen"}, {"rank": "48", "did": "DB14681", "name": "Cortisone"}, {"rank": "49", "did": "DB00305", "name": "Mitomycin"}, {"rank": "50", "did": "DB09069", "name": "Trimetazidine"}]