[{"rank": "1", "did": "DB00396", "name": "Progesterone"}, {"rank": "2", "did": "DB01118", "name": "Amiodarone"}, {"rank": "3", "did": "DB00252", "name": "Phenytoin"}, {"rank": "4", "did": "DB01195", "name": "Flecainide"}, {"rank": "5", "did": "DB00571", "name": "Propranolol"}, {"rank": "6", "did": "DB01221", "name": "Ketamine"}, {"rank": "7", "did": "DB00770", "name": "Alprostadil"}, {"rank": "8", "did": "DB00640", "name": "Adenosine"}, {"rank": "9", "did": "DB00755", "name": "Tretinoin"}, {"rank": "10", "did": "DB06403", "name": "Ambrisentan"}, {"rank": "11", "did": "DB00184", "name": "Nicotine"}, {"rank": "12", "did": "DB01240", "name": "Epoprostenol"}, {"rank": "13", "did": "DB00925", "name": "Phenoxybenzamine"}, {"rank": "14", "did": "DB14507", "name": "Lithium citrate"}, {"rank": "15", "did": "DB09140", "name": "Oxygen"}, {"rank": "16", "did": "DB00316", "name": "Acetaminophen"}, {"rank": "17", "did": "DB00907", "name": "Cocaine"}, {"rank": "18", "did": "DB00945", "name": "Acetylsalicylic acid"}, {"rank": "19", "did": "DB00633", "name": "Dexmedetomidine"}, {"rank": "20", "did": "DB00171", "name": "ATP"}, {"rank": "21", "did": "DB01197", "name": "Captopril"}, {"rank": "22", "did": "DB01065", "name": "Melatonin"}, {"rank": "23", "did": "DB00343", "name": "Diltiazem"}, {"rank": "24", "did": "DB00819", "name": "Acetazolamide"}, {"rank": "25", "did": "DB00182", "name": "Amphetamine"}, {"rank": "26", "did": "DB01200", "name": "Bromocriptine"}, {"rank": "27", "did": "DB01064", "name": "Isoprenaline"}, {"rank": "28", "did": "DB00446", "name": "Chloramphenicol"}, {"rank": "29", "did": "DB00877", "name": "Sirolimus"}, {"rank": "30", "did": "DB00422", "name": "Methylphenidate"}, {"rank": "31", "did": "DB00437", "name": "Allopurinol"}, {"rank": "32", "did": "DB00572", "name": "Atropine"}, {"rank": "33", "did": "DB12116", "name": "Epigallocatechin gallate"}, {"rank": "34", "did": "DB11091", "name": "Hydrogen peroxide"}, {"rank": "35", "did": "DB00178", "name": "Ramipril"}, {"rank": "36", "did": "DB01103", "name": "Quinacrine"}, {"rank": "37", "did": "DB00333", "name": "Methadone"}, {"rank": "38", "did": "DB04540", "name": "Cholesterol"}, {"rank": "39", "did": "DB00829", "name": "Diazepam"}, {"rank": "40", "did": "DB03128", "name": "Acetylcholine"}, {"rank": "41", "did": "DB00727", "name": "Nitroglycerin"}, {"rank": "42", "did": "DB00515", "name": "Cisplatin"}, {"rank": "43", "did": "DB01159", "name": "Halothane"}, {"rank": "44", "did": "DB09270", "name": "Ubidecarenone"}, {"rank": "45", "did": "DB00834", "name": "Mifepristone"}, {"rank": "46", "did": "DB00783", "name": "Estradiol"}, {"rank": "47", "did": "DB00583", "name": "Levocarnitine"}, {"rank": "48", "did": "DB04880", "name": "Enoximone"}, {"rank": "49", "did": "DB00682", "name": "Warfarin"}, {"rank": "50", "did": "DB00661", "name": "Verapamil"}]