[{"rank": "1", "did": "DB00122", "name": "Choline"}, {"rank": "2", "did": "DB00158", "name": "Folic acid"}, {"rank": "3", "did": "DB00171", "name": "ATP"}, {"rank": "4", "did": "DB00558", "name": "Zanamivir"}, {"rank": "5", "did": "DB00143", "name": "Glutathione"}, {"rank": "6", "did": "DB00443", "name": "Betamethasone"}, {"rank": "7", "did": "DB01241", "name": "Gemfibrozil"}, {"rank": "8", "did": "DB00712", "name": "Flurbiprofen"}, {"rank": "9", "did": "DB09322", "name": "Zinc sulfate"}, {"rank": "10", "did": "DB00107", "name": "Oxytocin"}, {"rank": "11", "did": "DB11118", "name": "Ammonia"}, {"rank": "12", "did": "DB11735", "name": "Galactose"}, {"rank": "13", "did": "DB01174", "name": "Phenobarbital"}, {"rank": "14", "did": "DB09270", "name": "Ubidecarenone"}, {"rank": "15", "did": "DB03904", "name": "Urea"}, {"rank": "16", "did": "DB00531", "name": "Cyclophosphamide"}, {"rank": "17", "did": "DB01862", "name": "Isopropyl beta-D-thiogalactopyranoside"}, {"rank": "18", "did": "DB09561", "name": "Sodium glycerophosphate"}, {"rank": "19", "did": "DB09262", "name": "Imidafenacin"}, {"rank": "20", "did": "DB00125", "name": "Arginine"}, {"rank": "21", "did": "DB11091", "name": "Hydrogen peroxide"}, {"rank": "22", "did": "DB14513", "name": "Magnesium"}, {"rank": "23", "did": "DB00198", "name": "Oseltamivir"}, {"rank": "24", "did": "DB11430", "name": "Monensin"}, {"rank": "25", "did": "DB00134", "name": "Methionine"}, {"rank": "26", "did": "DB00446", "name": "Chloramphenicol"}, {"rank": "27", "did": "DB09140", "name": "Oxygen"}, {"rank": "28", "did": "DB04630", "name": "Aldosterone"}, {"rank": "29", "did": "DB00140", "name": "Riboflavin"}, {"rank": "30", "did": "DB02134", "name": "Xanthine"}, {"rank": "31", "did": "DB00502", "name": "Haloperidol"}, {"rank": "32", "did": "DB04045", "name": "(R)-methylmalonyl-CoA"}, {"rank": "33", "did": "DB00175", "name": "Pravastatin"}, {"rank": "34", "did": "DB01118", "name": "Amiodarone"}, {"rank": "35", "did": "DB09153", "name": "Sodium chloride"}, {"rank": "36", "did": "DB11475", "name": "Tylosin"}, {"rank": "37", "did": "DB11126", "name": "Calcium gluconate"}, {"rank": "38", "did": "DB00829", "name": "Diazepam"}, {"rank": "39", "did": "DB11137", "name": "Molybdenum"}, {"rank": "40", "did": "DB00104", "name": "Octreotide"}, {"rank": "41", "did": "DB00165", "name": "Pyridoxine"}, {"rank": "42", "did": "DB14500", "name": "Potassium"}, {"rank": "43", "did": "DB00202", "name": "Succinylcholine"}, {"rank": "44", "did": "DB01373", "name": "Calcium"}, {"rank": "45", "did": "DB13831", "name": "Potassium permanganate"}, {"rank": "46", "did": "DB00434", "name": "Cyproheptadine"}, {"rank": "47", "did": "DB00907", "name": "Cocaine"}, {"rank": "48", "did": "DB12907", "name": "Mannose"}, {"rank": "49", "did": "DB00898", "name": "Ethanol"}, {"rank": "50", "did": "DB00515", "name": "Cisplatin"}]